look/__init__.py
look/looking.py
look/utils/__init__.py
look/utils/network.py
look/utils/utils_predict.py
python_look-0.1.0.dist-info/LICENSE
python_look-0.1.0.dist-info/METADATA
python_look-0.1.0.dist-info/WHEEL
python_look-0.1.0.dist-info/top_level.txt
python_look-0.1.0.dist-info/RECORD
