Metadata-Version: 2.1
Name: python-look
Version: 0.1.0
Summary: Simple wrapper code to run inference on images using the model and code from the Looking Repo from VITA-EPFL.
Home-page: https://github.com/cwittwer/look
Author: Carson Wittwer
Author-email: wittwer.carson@googlemail.com
License: MIT
Classifier: Development Status :: 4 - Beta
Classifier: Intended Audience :: Developers
Classifier: License :: OSI Approved :: MIT License
Classifier: Operating System :: OS Independent
Classifier: Programming Language :: Python :: 3.6
Classifier: Programming Language :: Python :: 3.7
Classifier: Programming Language :: Python :: 3.8
Classifier: Programming Language :: Python :: 3.9
Requires-Python: >=3.6, <3.10
License-File: LICENSE
Requires-Dist: tqdm
Requires-Dist: numpy
Requires-Dist: opencv-python (==4.7.0.72)
Requires-Dist: seaborn
Requires-Dist: matplotlib
Requires-Dist: torch
Requires-Dist: torchvision
Requires-Dist: openpifpaf (==0.13.11)
Requires-Dist: scikit-image (==0.19.3)
Requires-Dist: Pillow
Requires-Dist: scikit-learn
